{"path":"lucene/codecs/src/test/org/apache/lucene/codecs/block/TestBlockPostingsFormat3#assertTermsEnum(TermsEnum,TermsEnum,boolean).mjava","commits":[{"id":"746d604154f8744382434608bf4f14fd4892ae36","date":1349102351,"type":0,"author":"Robert Muir","isMerge":false,"pathNew":"lucene/codecs/src/test/org/apache/lucene/codecs/block/TestBlockPostingsFormat3#assertTermsEnum(TermsEnum,TermsEnum,boolean).mjava","pathOld":"/dev/null","sourceNew":"  /** \n   * checks the terms enum sequentially\n   * if deep is false, it does a 'shallow' test that doesnt go down to the docsenums\n   */\n  public void assertTermsEnum(TermsEnum leftTermsEnum, TermsEnum rightTermsEnum, boolean deep) throws Exception {\n    BytesRef term;\n    Bits randomBits = new RandomBits(MAXDOC, random().nextDouble(), random());\n    DocsAndPositionsEnum leftPositions = null;\n    DocsAndPositionsEnum rightPositions = null;\n    DocsEnum leftDocs = null;\n    DocsEnum rightDocs = null;\n    \n    while ((term = leftTermsEnum.next()) != null) {\n      assertEquals(term, rightTermsEnum.next());\n      assertTermStats(leftTermsEnum, rightTermsEnum);\n      if (deep) {\n        // with payloads + off\n        assertDocsAndPositionsEnum(leftPositions = leftTermsEnum.docsAndPositions(null, leftPositions),\n                                   rightPositions = rightTermsEnum.docsAndPositions(null, rightPositions));\n        assertDocsAndPositionsEnum(leftPositions = leftTermsEnum.docsAndPositions(randomBits, leftPositions),\n                                   rightPositions = rightTermsEnum.docsAndPositions(randomBits, rightPositions));\n\n        assertPositionsSkipping(leftTermsEnum.docFreq(), \n                                leftPositions = leftTermsEnum.docsAndPositions(null, leftPositions),\n                                rightPositions = rightTermsEnum.docsAndPositions(null, rightPositions));\n        assertPositionsSkipping(leftTermsEnum.docFreq(), \n                                leftPositions = leftTermsEnum.docsAndPositions(randomBits, leftPositions),\n                                rightPositions = rightTermsEnum.docsAndPositions(randomBits, rightPositions));\n        // with payloads only\n        assertDocsAndPositionsEnum(leftPositions = leftTermsEnum.docsAndPositions(null, leftPositions, DocsAndPositionsEnum.FLAG_PAYLOADS),\n                                   rightPositions = rightTermsEnum.docsAndPositions(null, rightPositions, DocsAndPositionsEnum.FLAG_PAYLOADS));\n        assertDocsAndPositionsEnum(leftPositions = leftTermsEnum.docsAndPositions(randomBits, leftPositions, DocsAndPositionsEnum.FLAG_PAYLOADS),\n                                   rightPositions = rightTermsEnum.docsAndPositions(randomBits, rightPositions, DocsAndPositionsEnum.FLAG_PAYLOADS));\n\n        assertPositionsSkipping(leftTermsEnum.docFreq(), \n                                leftPositions = leftTermsEnum.docsAndPositions(null, leftPositions, DocsAndPositionsEnum.FLAG_PAYLOADS),\n                                rightPositions = rightTermsEnum.docsAndPositions(null, rightPositions, DocsAndPositionsEnum.FLAG_PAYLOADS));\n        assertPositionsSkipping(leftTermsEnum.docFreq(), \n                                leftPositions = leftTermsEnum.docsAndPositions(randomBits, leftPositions, DocsAndPositionsEnum.FLAG_PAYLOADS),\n                                rightPositions = rightTermsEnum.docsAndPositions(randomBits, rightPositions, DocsAndPositionsEnum.FLAG_PAYLOADS));\n\n        // with offsets only\n        assertDocsAndPositionsEnum(leftPositions = leftTermsEnum.docsAndPositions(null, leftPositions, DocsAndPositionsEnum.FLAG_OFFSETS),\n                                   rightPositions = rightTermsEnum.docsAndPositions(null, rightPositions, DocsAndPositionsEnum.FLAG_OFFSETS));\n        assertDocsAndPositionsEnum(leftPositions = leftTermsEnum.docsAndPositions(randomBits, leftPositions, DocsAndPositionsEnum.FLAG_OFFSETS),\n                                   rightPositions = rightTermsEnum.docsAndPositions(randomBits, rightPositions, DocsAndPositionsEnum.FLAG_OFFSETS));\n\n        assertPositionsSkipping(leftTermsEnum.docFreq(), \n                                leftPositions = leftTermsEnum.docsAndPositions(null, leftPositions, DocsAndPositionsEnum.FLAG_OFFSETS),\n                                rightPositions = rightTermsEnum.docsAndPositions(null, rightPositions, DocsAndPositionsEnum.FLAG_OFFSETS));\n        assertPositionsSkipping(leftTermsEnum.docFreq(), \n                                leftPositions = leftTermsEnum.docsAndPositions(randomBits, leftPositions, DocsAndPositionsEnum.FLAG_OFFSETS),\n                                rightPositions = rightTermsEnum.docsAndPositions(randomBits, rightPositions, DocsAndPositionsEnum.FLAG_OFFSETS));\n        \n        // with positions only\n        assertDocsAndPositionsEnum(leftPositions = leftTermsEnum.docsAndPositions(null, leftPositions, 0),\n                                   rightPositions = rightTermsEnum.docsAndPositions(null, rightPositions, 0));\n        assertDocsAndPositionsEnum(leftPositions = leftTermsEnum.docsAndPositions(randomBits, leftPositions, 0),\n                                   rightPositions = rightTermsEnum.docsAndPositions(randomBits, rightPositions, 0));\n\n        assertPositionsSkipping(leftTermsEnum.docFreq(), \n                                leftPositions = leftTermsEnum.docsAndPositions(null, leftPositions, 0),\n                                rightPositions = rightTermsEnum.docsAndPositions(null, rightPositions, 0));\n        assertPositionsSkipping(leftTermsEnum.docFreq(), \n                                leftPositions = leftTermsEnum.docsAndPositions(randomBits, leftPositions, 0),\n                                rightPositions = rightTermsEnum.docsAndPositions(randomBits, rightPositions, 0));\n        \n        // with freqs:\n        assertDocsEnum(leftDocs = leftTermsEnum.docs(null, leftDocs),\n            rightDocs = rightTermsEnum.docs(null, rightDocs),\n            true);\n        assertDocsEnum(leftDocs = leftTermsEnum.docs(randomBits, leftDocs),\n            rightDocs = rightTermsEnum.docs(randomBits, rightDocs),\n            true);\n\n        // w/o freqs:\n        assertDocsEnum(leftDocs = leftTermsEnum.docs(null, leftDocs, 0),\n            rightDocs = rightTermsEnum.docs(null, rightDocs, 0),\n            false);\n        assertDocsEnum(leftDocs = leftTermsEnum.docs(randomBits, leftDocs, 0),\n            rightDocs = rightTermsEnum.docs(randomBits, rightDocs, 0),\n            false);\n        \n        // with freqs:\n        assertDocsSkipping(leftTermsEnum.docFreq(), \n            leftDocs = leftTermsEnum.docs(null, leftDocs),\n            rightDocs = rightTermsEnum.docs(null, rightDocs),\n            true);\n        assertDocsSkipping(leftTermsEnum.docFreq(), \n            leftDocs = leftTermsEnum.docs(randomBits, leftDocs),\n            rightDocs = rightTermsEnum.docs(randomBits, rightDocs),\n            true);\n\n        // w/o freqs:\n        assertDocsSkipping(leftTermsEnum.docFreq(), \n            leftDocs = leftTermsEnum.docs(null, leftDocs, 0),\n            rightDocs = rightTermsEnum.docs(null, rightDocs, 0),\n            false);\n        assertDocsSkipping(leftTermsEnum.docFreq(), \n            leftDocs = leftTermsEnum.docs(randomBits, leftDocs, 0),\n            rightDocs = rightTermsEnum.docs(randomBits, rightDocs, 0),\n            false);\n      }\n    }\n    assertNull(rightTermsEnum.next());\n  }\n\n","sourceOld":null,"bugFix":null,"bugIntro":[],"isBuggy":false,"nexts":[],"revCommit":null},{"id":"cf8086c7e11dc41303ef1b8050bd355ddfaee76d","date":1350007219,"type":5,"author":"Robert Muir","isMerge":false,"pathNew":"lucene/core/src/test/org/apache/lucene/codecs/lucene41/TestBlockPostingsFormat3#assertTermsEnum(TermsEnum,TermsEnum,boolean).mjava","pathOld":"lucene/codecs/src/test/org/apache/lucene/codecs/block/TestBlockPostingsFormat3#assertTermsEnum(TermsEnum,TermsEnum,boolean).mjava","sourceNew":"  /** \n   * checks the terms enum sequentially\n   * if deep is false, it does a 'shallow' test that doesnt go down to the docsenums\n   */\n  public void assertTermsEnum(TermsEnum leftTermsEnum, TermsEnum rightTermsEnum, boolean deep) throws Exception {\n    BytesRef term;\n    Bits randomBits = new RandomBits(MAXDOC, random().nextDouble(), random());\n    DocsAndPositionsEnum leftPositions = null;\n    DocsAndPositionsEnum rightPositions = null;\n    DocsEnum leftDocs = null;\n    DocsEnum rightDocs = null;\n    \n    while ((term = leftTermsEnum.next()) != null) {\n      assertEquals(term, rightTermsEnum.next());\n      assertTermStats(leftTermsEnum, rightTermsEnum);\n      if (deep) {\n        // with payloads + off\n        assertDocsAndPositionsEnum(leftPositions = leftTermsEnum.docsAndPositions(null, leftPositions),\n                                   rightPositions = rightTermsEnum.docsAndPositions(null, rightPositions));\n        assertDocsAndPositionsEnum(leftPositions = leftTermsEnum.docsAndPositions(randomBits, leftPositions),\n                                   rightPositions = rightTermsEnum.docsAndPositions(randomBits, rightPositions));\n\n        assertPositionsSkipping(leftTermsEnum.docFreq(), \n                                leftPositions = leftTermsEnum.docsAndPositions(null, leftPositions),\n                                rightPositions = rightTermsEnum.docsAndPositions(null, rightPositions));\n        assertPositionsSkipping(leftTermsEnum.docFreq(), \n                                leftPositions = leftTermsEnum.docsAndPositions(randomBits, leftPositions),\n                                rightPositions = rightTermsEnum.docsAndPositions(randomBits, rightPositions));\n        // with payloads only\n        assertDocsAndPositionsEnum(leftPositions = leftTermsEnum.docsAndPositions(null, leftPositions, DocsAndPositionsEnum.FLAG_PAYLOADS),\n                                   rightPositions = rightTermsEnum.docsAndPositions(null, rightPositions, DocsAndPositionsEnum.FLAG_PAYLOADS));\n        assertDocsAndPositionsEnum(leftPositions = leftTermsEnum.docsAndPositions(randomBits, leftPositions, DocsAndPositionsEnum.FLAG_PAYLOADS),\n                                   rightPositions = rightTermsEnum.docsAndPositions(randomBits, rightPositions, DocsAndPositionsEnum.FLAG_PAYLOADS));\n\n        assertPositionsSkipping(leftTermsEnum.docFreq(), \n                                leftPositions = leftTermsEnum.docsAndPositions(null, leftPositions, DocsAndPositionsEnum.FLAG_PAYLOADS),\n                                rightPositions = rightTermsEnum.docsAndPositions(null, rightPositions, DocsAndPositionsEnum.FLAG_PAYLOADS));\n        assertPositionsSkipping(leftTermsEnum.docFreq(), \n                                leftPositions = leftTermsEnum.docsAndPositions(randomBits, leftPositions, DocsAndPositionsEnum.FLAG_PAYLOADS),\n                                rightPositions = rightTermsEnum.docsAndPositions(randomBits, rightPositions, DocsAndPositionsEnum.FLAG_PAYLOADS));\n\n        // with offsets only\n        assertDocsAndPositionsEnum(leftPositions = leftTermsEnum.docsAndPositions(null, leftPositions, DocsAndPositionsEnum.FLAG_OFFSETS),\n                                   rightPositions = rightTermsEnum.docsAndPositions(null, rightPositions, DocsAndPositionsEnum.FLAG_OFFSETS));\n        assertDocsAndPositionsEnum(leftPositions = leftTermsEnum.docsAndPositions(randomBits, leftPositions, DocsAndPositionsEnum.FLAG_OFFSETS),\n                                   rightPositions = rightTermsEnum.docsAndPositions(randomBits, rightPositions, DocsAndPositionsEnum.FLAG_OFFSETS));\n\n        assertPositionsSkipping(leftTermsEnum.docFreq(), \n                                leftPositions = leftTermsEnum.docsAndPositions(null, leftPositions, DocsAndPositionsEnum.FLAG_OFFSETS),\n                                rightPositions = rightTermsEnum.docsAndPositions(null, rightPositions, DocsAndPositionsEnum.FLAG_OFFSETS));\n        assertPositionsSkipping(leftTermsEnum.docFreq(), \n                                leftPositions = leftTermsEnum.docsAndPositions(randomBits, leftPositions, DocsAndPositionsEnum.FLAG_OFFSETS),\n                                rightPositions = rightTermsEnum.docsAndPositions(randomBits, rightPositions, DocsAndPositionsEnum.FLAG_OFFSETS));\n        \n        // with positions only\n        assertDocsAndPositionsEnum(leftPositions = leftTermsEnum.docsAndPositions(null, leftPositions, 0),\n                                   rightPositions = rightTermsEnum.docsAndPositions(null, rightPositions, 0));\n        assertDocsAndPositionsEnum(leftPositions = leftTermsEnum.docsAndPositions(randomBits, leftPositions, 0),\n                                   rightPositions = rightTermsEnum.docsAndPositions(randomBits, rightPositions, 0));\n\n        assertPositionsSkipping(leftTermsEnum.docFreq(), \n                                leftPositions = leftTermsEnum.docsAndPositions(null, leftPositions, 0),\n                                rightPositions = rightTermsEnum.docsAndPositions(null, rightPositions, 0));\n        assertPositionsSkipping(leftTermsEnum.docFreq(), \n                                leftPositions = leftTermsEnum.docsAndPositions(randomBits, leftPositions, 0),\n                                rightPositions = rightTermsEnum.docsAndPositions(randomBits, rightPositions, 0));\n        \n        // with freqs:\n        assertDocsEnum(leftDocs = leftTermsEnum.docs(null, leftDocs),\n            rightDocs = rightTermsEnum.docs(null, rightDocs),\n            true);\n        assertDocsEnum(leftDocs = leftTermsEnum.docs(randomBits, leftDocs),\n            rightDocs = rightTermsEnum.docs(randomBits, rightDocs),\n            true);\n\n        // w/o freqs:\n        assertDocsEnum(leftDocs = leftTermsEnum.docs(null, leftDocs, 0),\n            rightDocs = rightTermsEnum.docs(null, rightDocs, 0),\n            false);\n        assertDocsEnum(leftDocs = leftTermsEnum.docs(randomBits, leftDocs, 0),\n            rightDocs = rightTermsEnum.docs(randomBits, rightDocs, 0),\n            false);\n        \n        // with freqs:\n        assertDocsSkipping(leftTermsEnum.docFreq(), \n            leftDocs = leftTermsEnum.docs(null, leftDocs),\n            rightDocs = rightTermsEnum.docs(null, rightDocs),\n            true);\n        assertDocsSkipping(leftTermsEnum.docFreq(), \n            leftDocs = leftTermsEnum.docs(randomBits, leftDocs),\n            rightDocs = rightTermsEnum.docs(randomBits, rightDocs),\n            true);\n\n        // w/o freqs:\n        assertDocsSkipping(leftTermsEnum.docFreq(), \n            leftDocs = leftTermsEnum.docs(null, leftDocs, 0),\n            rightDocs = rightTermsEnum.docs(null, rightDocs, 0),\n            false);\n        assertDocsSkipping(leftTermsEnum.docFreq(), \n            leftDocs = leftTermsEnum.docs(randomBits, leftDocs, 0),\n            rightDocs = rightTermsEnum.docs(randomBits, rightDocs, 0),\n            false);\n      }\n    }\n    assertNull(rightTermsEnum.next());\n  }\n\n","sourceOld":"  /** \n   * checks the terms enum sequentially\n   * if deep is false, it does a 'shallow' test that doesnt go down to the docsenums\n   */\n  public void assertTermsEnum(TermsEnum leftTermsEnum, TermsEnum rightTermsEnum, boolean deep) throws Exception {\n    BytesRef term;\n    Bits randomBits = new RandomBits(MAXDOC, random().nextDouble(), random());\n    DocsAndPositionsEnum leftPositions = null;\n    DocsAndPositionsEnum rightPositions = null;\n    DocsEnum leftDocs = null;\n    DocsEnum rightDocs = null;\n    \n    while ((term = leftTermsEnum.next()) != null) {\n      assertEquals(term, rightTermsEnum.next());\n      assertTermStats(leftTermsEnum, rightTermsEnum);\n      if (deep) {\n        // with payloads + off\n        assertDocsAndPositionsEnum(leftPositions = leftTermsEnum.docsAndPositions(null, leftPositions),\n                                   rightPositions = rightTermsEnum.docsAndPositions(null, rightPositions));\n        assertDocsAndPositionsEnum(leftPositions = leftTermsEnum.docsAndPositions(randomBits, leftPositions),\n                                   rightPositions = rightTermsEnum.docsAndPositions(randomBits, rightPositions));\n\n        assertPositionsSkipping(leftTermsEnum.docFreq(), \n                                leftPositions = leftTermsEnum.docsAndPositions(null, leftPositions),\n                                rightPositions = rightTermsEnum.docsAndPositions(null, rightPositions));\n        assertPositionsSkipping(leftTermsEnum.docFreq(), \n                                leftPositions = leftTermsEnum.docsAndPositions(randomBits, leftPositions),\n                                rightPositions = rightTermsEnum.docsAndPositions(randomBits, rightPositions));\n        // with payloads only\n        assertDocsAndPositionsEnum(leftPositions = leftTermsEnum.docsAndPositions(null, leftPositions, DocsAndPositionsEnum.FLAG_PAYLOADS),\n                                   rightPositions = rightTermsEnum.docsAndPositions(null, rightPositions, DocsAndPositionsEnum.FLAG_PAYLOADS));\n        assertDocsAndPositionsEnum(leftPositions = leftTermsEnum.docsAndPositions(randomBits, leftPositions, DocsAndPositionsEnum.FLAG_PAYLOADS),\n                                   rightPositions = rightTermsEnum.docsAndPositions(randomBits, rightPositions, DocsAndPositionsEnum.FLAG_PAYLOADS));\n\n        assertPositionsSkipping(leftTermsEnum.docFreq(), \n                                leftPositions = leftTermsEnum.docsAndPositions(null, leftPositions, DocsAndPositionsEnum.FLAG_PAYLOADS),\n                                rightPositions = rightTermsEnum.docsAndPositions(null, rightPositions, DocsAndPositionsEnum.FLAG_PAYLOADS));\n        assertPositionsSkipping(leftTermsEnum.docFreq(), \n                                leftPositions = leftTermsEnum.docsAndPositions(randomBits, leftPositions, DocsAndPositionsEnum.FLAG_PAYLOADS),\n                                rightPositions = rightTermsEnum.docsAndPositions(randomBits, rightPositions, DocsAndPositionsEnum.FLAG_PAYLOADS));\n\n        // with offsets only\n        assertDocsAndPositionsEnum(leftPositions = leftTermsEnum.docsAndPositions(null, leftPositions, DocsAndPositionsEnum.FLAG_OFFSETS),\n                                   rightPositions = rightTermsEnum.docsAndPositions(null, rightPositions, DocsAndPositionsEnum.FLAG_OFFSETS));\n        assertDocsAndPositionsEnum(leftPositions = leftTermsEnum.docsAndPositions(randomBits, leftPositions, DocsAndPositionsEnum.FLAG_OFFSETS),\n                                   rightPositions = rightTermsEnum.docsAndPositions(randomBits, rightPositions, DocsAndPositionsEnum.FLAG_OFFSETS));\n\n        assertPositionsSkipping(leftTermsEnum.docFreq(), \n                                leftPositions = leftTermsEnum.docsAndPositions(null, leftPositions, DocsAndPositionsEnum.FLAG_OFFSETS),\n                                rightPositions = rightTermsEnum.docsAndPositions(null, rightPositions, DocsAndPositionsEnum.FLAG_OFFSETS));\n        assertPositionsSkipping(leftTermsEnum.docFreq(), \n                                leftPositions = leftTermsEnum.docsAndPositions(randomBits, leftPositions, DocsAndPositionsEnum.FLAG_OFFSETS),\n                                rightPositions = rightTermsEnum.docsAndPositions(randomBits, rightPositions, DocsAndPositionsEnum.FLAG_OFFSETS));\n        \n        // with positions only\n        assertDocsAndPositionsEnum(leftPositions = leftTermsEnum.docsAndPositions(null, leftPositions, 0),\n                                   rightPositions = rightTermsEnum.docsAndPositions(null, rightPositions, 0));\n        assertDocsAndPositionsEnum(leftPositions = leftTermsEnum.docsAndPositions(randomBits, leftPositions, 0),\n                                   rightPositions = rightTermsEnum.docsAndPositions(randomBits, rightPositions, 0));\n\n        assertPositionsSkipping(leftTermsEnum.docFreq(), \n                                leftPositions = leftTermsEnum.docsAndPositions(null, leftPositions, 0),\n                                rightPositions = rightTermsEnum.docsAndPositions(null, rightPositions, 0));\n        assertPositionsSkipping(leftTermsEnum.docFreq(), \n                                leftPositions = leftTermsEnum.docsAndPositions(randomBits, leftPositions, 0),\n                                rightPositions = rightTermsEnum.docsAndPositions(randomBits, rightPositions, 0));\n        \n        // with freqs:\n        assertDocsEnum(leftDocs = leftTermsEnum.docs(null, leftDocs),\n            rightDocs = rightTermsEnum.docs(null, rightDocs),\n            true);\n        assertDocsEnum(leftDocs = leftTermsEnum.docs(randomBits, leftDocs),\n            rightDocs = rightTermsEnum.docs(randomBits, rightDocs),\n            true);\n\n        // w/o freqs:\n        assertDocsEnum(leftDocs = leftTermsEnum.docs(null, leftDocs, 0),\n            rightDocs = rightTermsEnum.docs(null, rightDocs, 0),\n            false);\n        assertDocsEnum(leftDocs = leftTermsEnum.docs(randomBits, leftDocs, 0),\n            rightDocs = rightTermsEnum.docs(randomBits, rightDocs, 0),\n            false);\n        \n        // with freqs:\n        assertDocsSkipping(leftTermsEnum.docFreq(), \n            leftDocs = leftTermsEnum.docs(null, leftDocs),\n            rightDocs = rightTermsEnum.docs(null, rightDocs),\n            true);\n        assertDocsSkipping(leftTermsEnum.docFreq(), \n            leftDocs = leftTermsEnum.docs(randomBits, leftDocs),\n            rightDocs = rightTermsEnum.docs(randomBits, rightDocs),\n            true);\n\n        // w/o freqs:\n        assertDocsSkipping(leftTermsEnum.docFreq(), \n            leftDocs = leftTermsEnum.docs(null, leftDocs, 0),\n            rightDocs = rightTermsEnum.docs(null, rightDocs, 0),\n            false);\n        assertDocsSkipping(leftTermsEnum.docFreq(), \n            leftDocs = leftTermsEnum.docs(randomBits, leftDocs, 0),\n            rightDocs = rightTermsEnum.docs(randomBits, rightDocs, 0),\n            false);\n      }\n    }\n    assertNull(rightTermsEnum.next());\n  }\n\n","bugFix":null,"bugIntro":[],"isBuggy":false,"nexts":[],"revCommit":null},{"id":"c7492bcb52be51e55d596134b95b2e53cc4ffb91","date":1350223278,"type":5,"author":"Robert Muir","isMerge":true,"pathNew":"lucene/core/src/test/org/apache/lucene/codecs/lucene41/TestBlockPostingsFormat3#assertTermsEnum(TermsEnum,TermsEnum,boolean).mjava","pathOld":"lucene/codecs/src/test/org/apache/lucene/codecs/block/TestBlockPostingsFormat3#assertTermsEnum(TermsEnum,TermsEnum,boolean).mjava","sourceNew":"  /** \n   * checks the terms enum sequentially\n   * if deep is false, it does a 'shallow' test that doesnt go down to the docsenums\n   */\n  public void assertTermsEnum(TermsEnum leftTermsEnum, TermsEnum rightTermsEnum, boolean deep) throws Exception {\n    BytesRef term;\n    Bits randomBits = new RandomBits(MAXDOC, random().nextDouble(), random());\n    DocsAndPositionsEnum leftPositions = null;\n    DocsAndPositionsEnum rightPositions = null;\n    DocsEnum leftDocs = null;\n    DocsEnum rightDocs = null;\n    \n    while ((term = leftTermsEnum.next()) != null) {\n      assertEquals(term, rightTermsEnum.next());\n      assertTermStats(leftTermsEnum, rightTermsEnum);\n      if (deep) {\n        // with payloads + off\n        assertDocsAndPositionsEnum(leftPositions = leftTermsEnum.docsAndPositions(null, leftPositions),\n                                   rightPositions = rightTermsEnum.docsAndPositions(null, rightPositions));\n        assertDocsAndPositionsEnum(leftPositions = leftTermsEnum.docsAndPositions(randomBits, leftPositions),\n                                   rightPositions = rightTermsEnum.docsAndPositions(randomBits, rightPositions));\n\n        assertPositionsSkipping(leftTermsEnum.docFreq(), \n                                leftPositions = leftTermsEnum.docsAndPositions(null, leftPositions),\n                                rightPositions = rightTermsEnum.docsAndPositions(null, rightPositions));\n        assertPositionsSkipping(leftTermsEnum.docFreq(), \n                                leftPositions = leftTermsEnum.docsAndPositions(randomBits, leftPositions),\n                                rightPositions = rightTermsEnum.docsAndPositions(randomBits, rightPositions));\n        // with payloads only\n        assertDocsAndPositionsEnum(leftPositions = leftTermsEnum.docsAndPositions(null, leftPositions, DocsAndPositionsEnum.FLAG_PAYLOADS),\n                                   rightPositions = rightTermsEnum.docsAndPositions(null, rightPositions, DocsAndPositionsEnum.FLAG_PAYLOADS));\n        assertDocsAndPositionsEnum(leftPositions = leftTermsEnum.docsAndPositions(randomBits, leftPositions, DocsAndPositionsEnum.FLAG_PAYLOADS),\n                                   rightPositions = rightTermsEnum.docsAndPositions(randomBits, rightPositions, DocsAndPositionsEnum.FLAG_PAYLOADS));\n\n        assertPositionsSkipping(leftTermsEnum.docFreq(), \n                                leftPositions = leftTermsEnum.docsAndPositions(null, leftPositions, DocsAndPositionsEnum.FLAG_PAYLOADS),\n                                rightPositions = rightTermsEnum.docsAndPositions(null, rightPositions, DocsAndPositionsEnum.FLAG_PAYLOADS));\n        assertPositionsSkipping(leftTermsEnum.docFreq(), \n                                leftPositions = leftTermsEnum.docsAndPositions(randomBits, leftPositions, DocsAndPositionsEnum.FLAG_PAYLOADS),\n                                rightPositions = rightTermsEnum.docsAndPositions(randomBits, rightPositions, DocsAndPositionsEnum.FLAG_PAYLOADS));\n\n        // with offsets only\n        assertDocsAndPositionsEnum(leftPositions = leftTermsEnum.docsAndPositions(null, leftPositions, DocsAndPositionsEnum.FLAG_OFFSETS),\n                                   rightPositions = rightTermsEnum.docsAndPositions(null, rightPositions, DocsAndPositionsEnum.FLAG_OFFSETS));\n        assertDocsAndPositionsEnum(leftPositions = leftTermsEnum.docsAndPositions(randomBits, leftPositions, DocsAndPositionsEnum.FLAG_OFFSETS),\n                                   rightPositions = rightTermsEnum.docsAndPositions(randomBits, rightPositions, DocsAndPositionsEnum.FLAG_OFFSETS));\n\n        assertPositionsSkipping(leftTermsEnum.docFreq(), \n                                leftPositions = leftTermsEnum.docsAndPositions(null, leftPositions, DocsAndPositionsEnum.FLAG_OFFSETS),\n                                rightPositions = rightTermsEnum.docsAndPositions(null, rightPositions, DocsAndPositionsEnum.FLAG_OFFSETS));\n        assertPositionsSkipping(leftTermsEnum.docFreq(), \n                                leftPositions = leftTermsEnum.docsAndPositions(randomBits, leftPositions, DocsAndPositionsEnum.FLAG_OFFSETS),\n                                rightPositions = rightTermsEnum.docsAndPositions(randomBits, rightPositions, DocsAndPositionsEnum.FLAG_OFFSETS));\n        \n        // with positions only\n        assertDocsAndPositionsEnum(leftPositions = leftTermsEnum.docsAndPositions(null, leftPositions, 0),\n                                   rightPositions = rightTermsEnum.docsAndPositions(null, rightPositions, 0));\n        assertDocsAndPositionsEnum(leftPositions = leftTermsEnum.docsAndPositions(randomBits, leftPositions, 0),\n                                   rightPositions = rightTermsEnum.docsAndPositions(randomBits, rightPositions, 0));\n\n        assertPositionsSkipping(leftTermsEnum.docFreq(), \n                                leftPositions = leftTermsEnum.docsAndPositions(null, leftPositions, 0),\n                                rightPositions = rightTermsEnum.docsAndPositions(null, rightPositions, 0));\n        assertPositionsSkipping(leftTermsEnum.docFreq(), \n                                leftPositions = leftTermsEnum.docsAndPositions(randomBits, leftPositions, 0),\n                                rightPositions = rightTermsEnum.docsAndPositions(randomBits, rightPositions, 0));\n        \n        // with freqs:\n        assertDocsEnum(leftDocs = leftTermsEnum.docs(null, leftDocs),\n            rightDocs = rightTermsEnum.docs(null, rightDocs),\n            true);\n        assertDocsEnum(leftDocs = leftTermsEnum.docs(randomBits, leftDocs),\n            rightDocs = rightTermsEnum.docs(randomBits, rightDocs),\n            true);\n\n        // w/o freqs:\n        assertDocsEnum(leftDocs = leftTermsEnum.docs(null, leftDocs, 0),\n            rightDocs = rightTermsEnum.docs(null, rightDocs, 0),\n            false);\n        assertDocsEnum(leftDocs = leftTermsEnum.docs(randomBits, leftDocs, 0),\n            rightDocs = rightTermsEnum.docs(randomBits, rightDocs, 0),\n            false);\n        \n        // with freqs:\n        assertDocsSkipping(leftTermsEnum.docFreq(), \n            leftDocs = leftTermsEnum.docs(null, leftDocs),\n            rightDocs = rightTermsEnum.docs(null, rightDocs),\n            true);\n        assertDocsSkipping(leftTermsEnum.docFreq(), \n            leftDocs = leftTermsEnum.docs(randomBits, leftDocs),\n            rightDocs = rightTermsEnum.docs(randomBits, rightDocs),\n            true);\n\n        // w/o freqs:\n        assertDocsSkipping(leftTermsEnum.docFreq(), \n            leftDocs = leftTermsEnum.docs(null, leftDocs, 0),\n            rightDocs = rightTermsEnum.docs(null, rightDocs, 0),\n            false);\n        assertDocsSkipping(leftTermsEnum.docFreq(), \n            leftDocs = leftTermsEnum.docs(randomBits, leftDocs, 0),\n            rightDocs = rightTermsEnum.docs(randomBits, rightDocs, 0),\n            false);\n      }\n    }\n    assertNull(rightTermsEnum.next());\n  }\n\n","sourceOld":"  /** \n   * checks the terms enum sequentially\n   * if deep is false, it does a 'shallow' test that doesnt go down to the docsenums\n   */\n  public void assertTermsEnum(TermsEnum leftTermsEnum, TermsEnum rightTermsEnum, boolean deep) throws Exception {\n    BytesRef term;\n    Bits randomBits = new RandomBits(MAXDOC, random().nextDouble(), random());\n    DocsAndPositionsEnum leftPositions = null;\n    DocsAndPositionsEnum rightPositions = null;\n    DocsEnum leftDocs = null;\n    DocsEnum rightDocs = null;\n    \n    while ((term = leftTermsEnum.next()) != null) {\n      assertEquals(term, rightTermsEnum.next());\n      assertTermStats(leftTermsEnum, rightTermsEnum);\n      if (deep) {\n        // with payloads + off\n        assertDocsAndPositionsEnum(leftPositions = leftTermsEnum.docsAndPositions(null, leftPositions),\n                                   rightPositions = rightTermsEnum.docsAndPositions(null, rightPositions));\n        assertDocsAndPositionsEnum(leftPositions = leftTermsEnum.docsAndPositions(randomBits, leftPositions),\n                                   rightPositions = rightTermsEnum.docsAndPositions(randomBits, rightPositions));\n\n        assertPositionsSkipping(leftTermsEnum.docFreq(), \n                                leftPositions = leftTermsEnum.docsAndPositions(null, leftPositions),\n                                rightPositions = rightTermsEnum.docsAndPositions(null, rightPositions));\n        assertPositionsSkipping(leftTermsEnum.docFreq(), \n                                leftPositions = leftTermsEnum.docsAndPositions(randomBits, leftPositions),\n                                rightPositions = rightTermsEnum.docsAndPositions(randomBits, rightPositions));\n        // with payloads only\n        assertDocsAndPositionsEnum(leftPositions = leftTermsEnum.docsAndPositions(null, leftPositions, DocsAndPositionsEnum.FLAG_PAYLOADS),\n                                   rightPositions = rightTermsEnum.docsAndPositions(null, rightPositions, DocsAndPositionsEnum.FLAG_PAYLOADS));\n        assertDocsAndPositionsEnum(leftPositions = leftTermsEnum.docsAndPositions(randomBits, leftPositions, DocsAndPositionsEnum.FLAG_PAYLOADS),\n                                   rightPositions = rightTermsEnum.docsAndPositions(randomBits, rightPositions, DocsAndPositionsEnum.FLAG_PAYLOADS));\n\n        assertPositionsSkipping(leftTermsEnum.docFreq(), \n                                leftPositions = leftTermsEnum.docsAndPositions(null, leftPositions, DocsAndPositionsEnum.FLAG_PAYLOADS),\n                                rightPositions = rightTermsEnum.docsAndPositions(null, rightPositions, DocsAndPositionsEnum.FLAG_PAYLOADS));\n        assertPositionsSkipping(leftTermsEnum.docFreq(), \n                                leftPositions = leftTermsEnum.docsAndPositions(randomBits, leftPositions, DocsAndPositionsEnum.FLAG_PAYLOADS),\n                                rightPositions = rightTermsEnum.docsAndPositions(randomBits, rightPositions, DocsAndPositionsEnum.FLAG_PAYLOADS));\n\n        // with offsets only\n        assertDocsAndPositionsEnum(leftPositions = leftTermsEnum.docsAndPositions(null, leftPositions, DocsAndPositionsEnum.FLAG_OFFSETS),\n                                   rightPositions = rightTermsEnum.docsAndPositions(null, rightPositions, DocsAndPositionsEnum.FLAG_OFFSETS));\n        assertDocsAndPositionsEnum(leftPositions = leftTermsEnum.docsAndPositions(randomBits, leftPositions, DocsAndPositionsEnum.FLAG_OFFSETS),\n                                   rightPositions = rightTermsEnum.docsAndPositions(randomBits, rightPositions, DocsAndPositionsEnum.FLAG_OFFSETS));\n\n        assertPositionsSkipping(leftTermsEnum.docFreq(), \n                                leftPositions = leftTermsEnum.docsAndPositions(null, leftPositions, DocsAndPositionsEnum.FLAG_OFFSETS),\n                                rightPositions = rightTermsEnum.docsAndPositions(null, rightPositions, DocsAndPositionsEnum.FLAG_OFFSETS));\n        assertPositionsSkipping(leftTermsEnum.docFreq(), \n                                leftPositions = leftTermsEnum.docsAndPositions(randomBits, leftPositions, DocsAndPositionsEnum.FLAG_OFFSETS),\n                                rightPositions = rightTermsEnum.docsAndPositions(randomBits, rightPositions, DocsAndPositionsEnum.FLAG_OFFSETS));\n        \n        // with positions only\n        assertDocsAndPositionsEnum(leftPositions = leftTermsEnum.docsAndPositions(null, leftPositions, 0),\n                                   rightPositions = rightTermsEnum.docsAndPositions(null, rightPositions, 0));\n        assertDocsAndPositionsEnum(leftPositions = leftTermsEnum.docsAndPositions(randomBits, leftPositions, 0),\n                                   rightPositions = rightTermsEnum.docsAndPositions(randomBits, rightPositions, 0));\n\n        assertPositionsSkipping(leftTermsEnum.docFreq(), \n                                leftPositions = leftTermsEnum.docsAndPositions(null, leftPositions, 0),\n                                rightPositions = rightTermsEnum.docsAndPositions(null, rightPositions, 0));\n        assertPositionsSkipping(leftTermsEnum.docFreq(), \n                                leftPositions = leftTermsEnum.docsAndPositions(randomBits, leftPositions, 0),\n                                rightPositions = rightTermsEnum.docsAndPositions(randomBits, rightPositions, 0));\n        \n        // with freqs:\n        assertDocsEnum(leftDocs = leftTermsEnum.docs(null, leftDocs),\n            rightDocs = rightTermsEnum.docs(null, rightDocs),\n            true);\n        assertDocsEnum(leftDocs = leftTermsEnum.docs(randomBits, leftDocs),\n            rightDocs = rightTermsEnum.docs(randomBits, rightDocs),\n            true);\n\n        // w/o freqs:\n        assertDocsEnum(leftDocs = leftTermsEnum.docs(null, leftDocs, 0),\n            rightDocs = rightTermsEnum.docs(null, rightDocs, 0),\n            false);\n        assertDocsEnum(leftDocs = leftTermsEnum.docs(randomBits, leftDocs, 0),\n            rightDocs = rightTermsEnum.docs(randomBits, rightDocs, 0),\n            false);\n        \n        // with freqs:\n        assertDocsSkipping(leftTermsEnum.docFreq(), \n            leftDocs = leftTermsEnum.docs(null, leftDocs),\n            rightDocs = rightTermsEnum.docs(null, rightDocs),\n            true);\n        assertDocsSkipping(leftTermsEnum.docFreq(), \n            leftDocs = leftTermsEnum.docs(randomBits, leftDocs),\n            rightDocs = rightTermsEnum.docs(randomBits, rightDocs),\n            true);\n\n        // w/o freqs:\n        assertDocsSkipping(leftTermsEnum.docFreq(), \n            leftDocs = leftTermsEnum.docs(null, leftDocs, 0),\n            rightDocs = rightTermsEnum.docs(null, rightDocs, 0),\n            false);\n        assertDocsSkipping(leftTermsEnum.docFreq(), \n            leftDocs = leftTermsEnum.docs(randomBits, leftDocs, 0),\n            rightDocs = rightTermsEnum.docs(randomBits, rightDocs, 0),\n            false);\n      }\n    }\n    assertNull(rightTermsEnum.next());\n  }\n\n","bugFix":null,"bugIntro":[],"isBuggy":false,"nexts":[],"revCommit":null},{"id":"db4fdbf3d262768eabc027cd8321edca0cd11fa8","date":1350574784,"type":5,"author":"Simon Willnauer","isMerge":true,"pathNew":"lucene/core/src/test/org/apache/lucene/codecs/lucene41/TestBlockPostingsFormat3#assertTermsEnum(TermsEnum,TermsEnum,boolean).mjava","pathOld":"lucene/codecs/src/test/org/apache/lucene/codecs/block/TestBlockPostingsFormat3#assertTermsEnum(TermsEnum,TermsEnum,boolean).mjava","sourceNew":"  /** \n   * checks the terms enum sequentially\n   * if deep is false, it does a 'shallow' test that doesnt go down to the docsenums\n   */\n  public void assertTermsEnum(TermsEnum leftTermsEnum, TermsEnum rightTermsEnum, boolean deep) throws Exception {\n    BytesRef term;\n    Bits randomBits = new RandomBits(MAXDOC, random().nextDouble(), random());\n    DocsAndPositionsEnum leftPositions = null;\n    DocsAndPositionsEnum rightPositions = null;\n    DocsEnum leftDocs = null;\n    DocsEnum rightDocs = null;\n    \n    while ((term = leftTermsEnum.next()) != null) {\n      assertEquals(term, rightTermsEnum.next());\n      assertTermStats(leftTermsEnum, rightTermsEnum);\n      if (deep) {\n        // with payloads + off\n        assertDocsAndPositionsEnum(leftPositions = leftTermsEnum.docsAndPositions(null, leftPositions),\n                                   rightPositions = rightTermsEnum.docsAndPositions(null, rightPositions));\n        assertDocsAndPositionsEnum(leftPositions = leftTermsEnum.docsAndPositions(randomBits, leftPositions),\n                                   rightPositions = rightTermsEnum.docsAndPositions(randomBits, rightPositions));\n\n        assertPositionsSkipping(leftTermsEnum.docFreq(), \n                                leftPositions = leftTermsEnum.docsAndPositions(null, leftPositions),\n                                rightPositions = rightTermsEnum.docsAndPositions(null, rightPositions));\n        assertPositionsSkipping(leftTermsEnum.docFreq(), \n                                leftPositions = leftTermsEnum.docsAndPositions(randomBits, leftPositions),\n                                rightPositions = rightTermsEnum.docsAndPositions(randomBits, rightPositions));\n        // with payloads only\n        assertDocsAndPositionsEnum(leftPositions = leftTermsEnum.docsAndPositions(null, leftPositions, DocsAndPositionsEnum.FLAG_PAYLOADS),\n                                   rightPositions = rightTermsEnum.docsAndPositions(null, rightPositions, DocsAndPositionsEnum.FLAG_PAYLOADS));\n        assertDocsAndPositionsEnum(leftPositions = leftTermsEnum.docsAndPositions(randomBits, leftPositions, DocsAndPositionsEnum.FLAG_PAYLOADS),\n                                   rightPositions = rightTermsEnum.docsAndPositions(randomBits, rightPositions, DocsAndPositionsEnum.FLAG_PAYLOADS));\n\n        assertPositionsSkipping(leftTermsEnum.docFreq(), \n                                leftPositions = leftTermsEnum.docsAndPositions(null, leftPositions, DocsAndPositionsEnum.FLAG_PAYLOADS),\n                                rightPositions = rightTermsEnum.docsAndPositions(null, rightPositions, DocsAndPositionsEnum.FLAG_PAYLOADS));\n        assertPositionsSkipping(leftTermsEnum.docFreq(), \n                                leftPositions = leftTermsEnum.docsAndPositions(randomBits, leftPositions, DocsAndPositionsEnum.FLAG_PAYLOADS),\n                                rightPositions = rightTermsEnum.docsAndPositions(randomBits, rightPositions, DocsAndPositionsEnum.FLAG_PAYLOADS));\n\n        // with offsets only\n        assertDocsAndPositionsEnum(leftPositions = leftTermsEnum.docsAndPositions(null, leftPositions, DocsAndPositionsEnum.FLAG_OFFSETS),\n                                   rightPositions = rightTermsEnum.docsAndPositions(null, rightPositions, DocsAndPositionsEnum.FLAG_OFFSETS));\n        assertDocsAndPositionsEnum(leftPositions = leftTermsEnum.docsAndPositions(randomBits, leftPositions, DocsAndPositionsEnum.FLAG_OFFSETS),\n                                   rightPositions = rightTermsEnum.docsAndPositions(randomBits, rightPositions, DocsAndPositionsEnum.FLAG_OFFSETS));\n\n        assertPositionsSkipping(leftTermsEnum.docFreq(), \n                                leftPositions = leftTermsEnum.docsAndPositions(null, leftPositions, DocsAndPositionsEnum.FLAG_OFFSETS),\n                                rightPositions = rightTermsEnum.docsAndPositions(null, rightPositions, DocsAndPositionsEnum.FLAG_OFFSETS));\n        assertPositionsSkipping(leftTermsEnum.docFreq(), \n                                leftPositions = leftTermsEnum.docsAndPositions(randomBits, leftPositions, DocsAndPositionsEnum.FLAG_OFFSETS),\n                                rightPositions = rightTermsEnum.docsAndPositions(randomBits, rightPositions, DocsAndPositionsEnum.FLAG_OFFSETS));\n        \n        // with positions only\n        assertDocsAndPositionsEnum(leftPositions = leftTermsEnum.docsAndPositions(null, leftPositions, 0),\n                                   rightPositions = rightTermsEnum.docsAndPositions(null, rightPositions, 0));\n        assertDocsAndPositionsEnum(leftPositions = leftTermsEnum.docsAndPositions(randomBits, leftPositions, 0),\n                                   rightPositions = rightTermsEnum.docsAndPositions(randomBits, rightPositions, 0));\n\n        assertPositionsSkipping(leftTermsEnum.docFreq(), \n                                leftPositions = leftTermsEnum.docsAndPositions(null, leftPositions, 0),\n                                rightPositions = rightTermsEnum.docsAndPositions(null, rightPositions, 0));\n        assertPositionsSkipping(leftTermsEnum.docFreq(), \n                                leftPositions = leftTermsEnum.docsAndPositions(randomBits, leftPositions, 0),\n                                rightPositions = rightTermsEnum.docsAndPositions(randomBits, rightPositions, 0));\n        \n        // with freqs:\n        assertDocsEnum(leftDocs = leftTermsEnum.docs(null, leftDocs),\n            rightDocs = rightTermsEnum.docs(null, rightDocs),\n            true);\n        assertDocsEnum(leftDocs = leftTermsEnum.docs(randomBits, leftDocs),\n            rightDocs = rightTermsEnum.docs(randomBits, rightDocs),\n            true);\n\n        // w/o freqs:\n        assertDocsEnum(leftDocs = leftTermsEnum.docs(null, leftDocs, 0),\n            rightDocs = rightTermsEnum.docs(null, rightDocs, 0),\n            false);\n        assertDocsEnum(leftDocs = leftTermsEnum.docs(randomBits, leftDocs, 0),\n            rightDocs = rightTermsEnum.docs(randomBits, rightDocs, 0),\n            false);\n        \n        // with freqs:\n        assertDocsSkipping(leftTermsEnum.docFreq(), \n            leftDocs = leftTermsEnum.docs(null, leftDocs),\n            rightDocs = rightTermsEnum.docs(null, rightDocs),\n            true);\n        assertDocsSkipping(leftTermsEnum.docFreq(), \n            leftDocs = leftTermsEnum.docs(randomBits, leftDocs),\n            rightDocs = rightTermsEnum.docs(randomBits, rightDocs),\n            true);\n\n        // w/o freqs:\n        assertDocsSkipping(leftTermsEnum.docFreq(), \n            leftDocs = leftTermsEnum.docs(null, leftDocs, 0),\n            rightDocs = rightTermsEnum.docs(null, rightDocs, 0),\n            false);\n        assertDocsSkipping(leftTermsEnum.docFreq(), \n            leftDocs = leftTermsEnum.docs(randomBits, leftDocs, 0),\n            rightDocs = rightTermsEnum.docs(randomBits, rightDocs, 0),\n            false);\n      }\n    }\n    assertNull(rightTermsEnum.next());\n  }\n\n","sourceOld":"  /** \n   * checks the terms enum sequentially\n   * if deep is false, it does a 'shallow' test that doesnt go down to the docsenums\n   */\n  public void assertTermsEnum(TermsEnum leftTermsEnum, TermsEnum rightTermsEnum, boolean deep) throws Exception {\n    BytesRef term;\n    Bits randomBits = new RandomBits(MAXDOC, random().nextDouble(), random());\n    DocsAndPositionsEnum leftPositions = null;\n    DocsAndPositionsEnum rightPositions = null;\n    DocsEnum leftDocs = null;\n    DocsEnum rightDocs = null;\n    \n    while ((term = leftTermsEnum.next()) != null) {\n      assertEquals(term, rightTermsEnum.next());\n      assertTermStats(leftTermsEnum, rightTermsEnum);\n      if (deep) {\n        // with payloads + off\n        assertDocsAndPositionsEnum(leftPositions = leftTermsEnum.docsAndPositions(null, leftPositions),\n                                   rightPositions = rightTermsEnum.docsAndPositions(null, rightPositions));\n        assertDocsAndPositionsEnum(leftPositions = leftTermsEnum.docsAndPositions(randomBits, leftPositions),\n                                   rightPositions = rightTermsEnum.docsAndPositions(randomBits, rightPositions));\n\n        assertPositionsSkipping(leftTermsEnum.docFreq(), \n                                leftPositions = leftTermsEnum.docsAndPositions(null, leftPositions),\n                                rightPositions = rightTermsEnum.docsAndPositions(null, rightPositions));\n        assertPositionsSkipping(leftTermsEnum.docFreq(), \n                                leftPositions = leftTermsEnum.docsAndPositions(randomBits, leftPositions),\n                                rightPositions = rightTermsEnum.docsAndPositions(randomBits, rightPositions));\n        // with payloads only\n        assertDocsAndPositionsEnum(leftPositions = leftTermsEnum.docsAndPositions(null, leftPositions, DocsAndPositionsEnum.FLAG_PAYLOADS),\n                                   rightPositions = rightTermsEnum.docsAndPositions(null, rightPositions, DocsAndPositionsEnum.FLAG_PAYLOADS));\n        assertDocsAndPositionsEnum(leftPositions = leftTermsEnum.docsAndPositions(randomBits, leftPositions, DocsAndPositionsEnum.FLAG_PAYLOADS),\n                                   rightPositions = rightTermsEnum.docsAndPositions(randomBits, rightPositions, DocsAndPositionsEnum.FLAG_PAYLOADS));\n\n        assertPositionsSkipping(leftTermsEnum.docFreq(), \n                                leftPositions = leftTermsEnum.docsAndPositions(null, leftPositions, DocsAndPositionsEnum.FLAG_PAYLOADS),\n                                rightPositions = rightTermsEnum.docsAndPositions(null, rightPositions, DocsAndPositionsEnum.FLAG_PAYLOADS));\n        assertPositionsSkipping(leftTermsEnum.docFreq(), \n                                leftPositions = leftTermsEnum.docsAndPositions(randomBits, leftPositions, DocsAndPositionsEnum.FLAG_PAYLOADS),\n                                rightPositions = rightTermsEnum.docsAndPositions(randomBits, rightPositions, DocsAndPositionsEnum.FLAG_PAYLOADS));\n\n        // with offsets only\n        assertDocsAndPositionsEnum(leftPositions = leftTermsEnum.docsAndPositions(null, leftPositions, DocsAndPositionsEnum.FLAG_OFFSETS),\n                                   rightPositions = rightTermsEnum.docsAndPositions(null, rightPositions, DocsAndPositionsEnum.FLAG_OFFSETS));\n        assertDocsAndPositionsEnum(leftPositions = leftTermsEnum.docsAndPositions(randomBits, leftPositions, DocsAndPositionsEnum.FLAG_OFFSETS),\n                                   rightPositions = rightTermsEnum.docsAndPositions(randomBits, rightPositions, DocsAndPositionsEnum.FLAG_OFFSETS));\n\n        assertPositionsSkipping(leftTermsEnum.docFreq(), \n                                leftPositions = leftTermsEnum.docsAndPositions(null, leftPositions, DocsAndPositionsEnum.FLAG_OFFSETS),\n                                rightPositions = rightTermsEnum.docsAndPositions(null, rightPositions, DocsAndPositionsEnum.FLAG_OFFSETS));\n        assertPositionsSkipping(leftTermsEnum.docFreq(), \n                                leftPositions = leftTermsEnum.docsAndPositions(randomBits, leftPositions, DocsAndPositionsEnum.FLAG_OFFSETS),\n                                rightPositions = rightTermsEnum.docsAndPositions(randomBits, rightPositions, DocsAndPositionsEnum.FLAG_OFFSETS));\n        \n        // with positions only\n        assertDocsAndPositionsEnum(leftPositions = leftTermsEnum.docsAndPositions(null, leftPositions, 0),\n                                   rightPositions = rightTermsEnum.docsAndPositions(null, rightPositions, 0));\n        assertDocsAndPositionsEnum(leftPositions = leftTermsEnum.docsAndPositions(randomBits, leftPositions, 0),\n                                   rightPositions = rightTermsEnum.docsAndPositions(randomBits, rightPositions, 0));\n\n        assertPositionsSkipping(leftTermsEnum.docFreq(), \n                                leftPositions = leftTermsEnum.docsAndPositions(null, leftPositions, 0),\n                                rightPositions = rightTermsEnum.docsAndPositions(null, rightPositions, 0));\n        assertPositionsSkipping(leftTermsEnum.docFreq(), \n                                leftPositions = leftTermsEnum.docsAndPositions(randomBits, leftPositions, 0),\n                                rightPositions = rightTermsEnum.docsAndPositions(randomBits, rightPositions, 0));\n        \n        // with freqs:\n        assertDocsEnum(leftDocs = leftTermsEnum.docs(null, leftDocs),\n            rightDocs = rightTermsEnum.docs(null, rightDocs),\n            true);\n        assertDocsEnum(leftDocs = leftTermsEnum.docs(randomBits, leftDocs),\n            rightDocs = rightTermsEnum.docs(randomBits, rightDocs),\n            true);\n\n        // w/o freqs:\n        assertDocsEnum(leftDocs = leftTermsEnum.docs(null, leftDocs, 0),\n            rightDocs = rightTermsEnum.docs(null, rightDocs, 0),\n            false);\n        assertDocsEnum(leftDocs = leftTermsEnum.docs(randomBits, leftDocs, 0),\n            rightDocs = rightTermsEnum.docs(randomBits, rightDocs, 0),\n            false);\n        \n        // with freqs:\n        assertDocsSkipping(leftTermsEnum.docFreq(), \n            leftDocs = leftTermsEnum.docs(null, leftDocs),\n            rightDocs = rightTermsEnum.docs(null, rightDocs),\n            true);\n        assertDocsSkipping(leftTermsEnum.docFreq(), \n            leftDocs = leftTermsEnum.docs(randomBits, leftDocs),\n            rightDocs = rightTermsEnum.docs(randomBits, rightDocs),\n            true);\n\n        // w/o freqs:\n        assertDocsSkipping(leftTermsEnum.docFreq(), \n            leftDocs = leftTermsEnum.docs(null, leftDocs, 0),\n            rightDocs = rightTermsEnum.docs(null, rightDocs, 0),\n            false);\n        assertDocsSkipping(leftTermsEnum.docFreq(), \n            leftDocs = leftTermsEnum.docs(randomBits, leftDocs, 0),\n            rightDocs = rightTermsEnum.docs(randomBits, rightDocs, 0),\n            false);\n      }\n    }\n    assertNull(rightTermsEnum.next());\n  }\n\n","bugFix":null,"bugIntro":[],"isBuggy":false,"nexts":[],"revCommit":null}],"commit2Parents":{"c7492bcb52be51e55d596134b95b2e53cc4ffb91":["746d604154f8744382434608bf4f14fd4892ae36","cf8086c7e11dc41303ef1b8050bd355ddfaee76d"],"cf8086c7e11dc41303ef1b8050bd355ddfaee76d":["746d604154f8744382434608bf4f14fd4892ae36"],"a0e7ee9d0d12370e8d2b5ae0a23b6e687e018d85":[],"db4fdbf3d262768eabc027cd8321edca0cd11fa8":["746d604154f8744382434608bf4f14fd4892ae36","c7492bcb52be51e55d596134b95b2e53cc4ffb91"],"746d604154f8744382434608bf4f14fd4892ae36":["a0e7ee9d0d12370e8d2b5ae0a23b6e687e018d85"],"cd5edd1f2b162a5cfa08efd17851a07373a96817":["c7492bcb52be51e55d596134b95b2e53cc4ffb91"]},"commit2Childs":{"c7492bcb52be51e55d596134b95b2e53cc4ffb91":["db4fdbf3d262768eabc027cd8321edca0cd11fa8","cd5edd1f2b162a5cfa08efd17851a07373a96817"],"cf8086c7e11dc41303ef1b8050bd355ddfaee76d":["c7492bcb52be51e55d596134b95b2e53cc4ffb91"],"a0e7ee9d0d12370e8d2b5ae0a23b6e687e018d85":["746d604154f8744382434608bf4f14fd4892ae36"],"db4fdbf3d262768eabc027cd8321edca0cd11fa8":[],"746d604154f8744382434608bf4f14fd4892ae36":["c7492bcb52be51e55d596134b95b2e53cc4ffb91","cf8086c7e11dc41303ef1b8050bd355ddfaee76d","db4fdbf3d262768eabc027cd8321edca0cd11fa8"],"cd5edd1f2b162a5cfa08efd17851a07373a96817":[]},"heads":["db4fdbf3d262768eabc027cd8321edca0cd11fa8","cd5edd1f2b162a5cfa08efd17851a07373a96817"],"roots":["a0e7ee9d0d12370e8d2b5ae0a23b6e687e018d85"],"pathCommit":null}