{"path":"lucene/backward-codecs/src/test/org/apache/lucene/codecs/lucene41/TestLucene41ForUtil#testEncodeDecode().mjava","commits":[{"id":"99eb4a732d1a908f4636ace52928876136bf1896","date":1413829552,"type":1,"author":"Robert Muir","isMerge":false,"pathNew":"lucene/backward-codecs/src/test/org/apache/lucene/codecs/lucene41/TestLucene41ForUtil#testEncodeDecode().mjava","pathOld":"lucene/core/src/test/org/apache/lucene/codecs/lucene41/TestForUtil#testEncodeDecode().mjava","sourceNew":"  public void testEncodeDecode() throws IOException {\n    final int iterations = RandomInts.randomIntBetween(random(), 1, 1000);\n    final float acceptableOverheadRatio = random().nextFloat();\n    final int[] values = new int[(iterations - 1) * BLOCK_SIZE + ForUtil.MAX_DATA_SIZE];\n    for (int i = 0; i < iterations; ++i) {\n      final int bpv = random().nextInt(32);\n      if (bpv == 0) {\n        final int value = RandomInts.randomIntBetween(random(), 0, Integer.MAX_VALUE);\n        for (int j = 0; j < BLOCK_SIZE; ++j) {\n          values[i * BLOCK_SIZE + j] = value;\n        }\n      } else {\n        for (int j = 0; j < BLOCK_SIZE; ++j) {\n          values[i * BLOCK_SIZE + j] = RandomInts.randomIntBetween(random(),\n              0, (int) PackedInts.maxValue(bpv));\n        }\n      }\n    }\n\n    final Directory d = new RAMDirectory();\n    final long endPointer;\n\n    {\n      // encode\n      IndexOutput out = d.createOutput(\"test.bin\", IOContext.DEFAULT);\n      final ForUtil forUtil = new ForUtil(acceptableOverheadRatio, out);\n      \n      for (int i = 0; i < iterations; ++i) {\n        forUtil.writeBlock(\n            Arrays.copyOfRange(values, i * BLOCK_SIZE, values.length),\n            new byte[MAX_ENCODED_SIZE], out);\n      }\n      endPointer = out.getFilePointer();\n      out.close();\n    }\n\n    {\n      // decode\n      IndexInput in = d.openInput(\"test.bin\", IOContext.READONCE);\n      final ForUtil forUtil = new ForUtil(in);\n      for (int i = 0; i < iterations; ++i) {\n        if (random().nextBoolean()) {\n          forUtil.skipBlock(in);\n          continue;\n        }\n        final int[] restored = new int[MAX_DATA_SIZE];\n        forUtil.readBlock(in, new byte[MAX_ENCODED_SIZE], restored);\n        assertArrayEquals(Arrays.copyOfRange(values, i * BLOCK_SIZE, (i + 1) * BLOCK_SIZE),\n            Arrays.copyOf(restored, BLOCK_SIZE));\n      }\n      assertEquals(endPointer, in.getFilePointer());\n      in.close();\n    }\n  }\n\n","sourceOld":"  public void testEncodeDecode() throws IOException {\n    final int iterations = RandomInts.randomIntBetween(random(), 1, 1000);\n    final float acceptableOverheadRatio = random().nextFloat();\n    final int[] values = new int[(iterations - 1) * BLOCK_SIZE + ForUtil.MAX_DATA_SIZE];\n    for (int i = 0; i < iterations; ++i) {\n      final int bpv = random().nextInt(32);\n      if (bpv == 0) {\n        final int value = RandomInts.randomIntBetween(random(), 0, Integer.MAX_VALUE);\n        for (int j = 0; j < BLOCK_SIZE; ++j) {\n          values[i * BLOCK_SIZE + j] = value;\n        }\n      } else {\n        for (int j = 0; j < BLOCK_SIZE; ++j) {\n          values[i * BLOCK_SIZE + j] = RandomInts.randomIntBetween(random(),\n              0, (int) PackedInts.maxValue(bpv));\n        }\n      }\n    }\n\n    final Directory d = new RAMDirectory();\n    final long endPointer;\n\n    {\n      // encode\n      IndexOutput out = d.createOutput(\"test.bin\", IOContext.DEFAULT);\n      final ForUtil forUtil = new ForUtil(acceptableOverheadRatio, out);\n      \n      for (int i = 0; i < iterations; ++i) {\n        forUtil.writeBlock(\n            Arrays.copyOfRange(values, i * BLOCK_SIZE, values.length),\n            new byte[MAX_ENCODED_SIZE], out);\n      }\n      endPointer = out.getFilePointer();\n      out.close();\n    }\n\n    {\n      // decode\n      IndexInput in = d.openInput(\"test.bin\", IOContext.READONCE);\n      final ForUtil forUtil = new ForUtil(in);\n      for (int i = 0; i < iterations; ++i) {\n        if (random().nextBoolean()) {\n          forUtil.skipBlock(in);\n          continue;\n        }\n        final int[] restored = new int[MAX_DATA_SIZE];\n        forUtil.readBlock(in, new byte[MAX_ENCODED_SIZE], restored);\n        assertArrayEquals(Arrays.copyOfRange(values, i * BLOCK_SIZE, (i + 1) * BLOCK_SIZE),\n            Arrays.copyOf(restored, BLOCK_SIZE));\n      }\n      assertEquals(endPointer, in.getFilePointer());\n      in.close();\n    }\n  }\n\n","bugFix":null,"bugIntro":[],"isBuggy":false,"nexts":[],"revCommit":null},{"id":"db68c63cbfaa8698b9c4475f75ed2b9c9696d238","date":1414118621,"type":1,"author":"Robert Muir","isMerge":true,"pathNew":"lucene/backward-codecs/src/test/org/apache/lucene/codecs/lucene41/TestLucene41ForUtil#testEncodeDecode().mjava","pathOld":"lucene/core/src/test/org/apache/lucene/codecs/lucene41/TestForUtil#testEncodeDecode().mjava","sourceNew":"  public void testEncodeDecode() throws IOException {\n    final int iterations = RandomInts.randomIntBetween(random(), 1, 1000);\n    final float acceptableOverheadRatio = random().nextFloat();\n    final int[] values = new int[(iterations - 1) * BLOCK_SIZE + ForUtil.MAX_DATA_SIZE];\n    for (int i = 0; i < iterations; ++i) {\n      final int bpv = random().nextInt(32);\n      if (bpv == 0) {\n        final int value = RandomInts.randomIntBetween(random(), 0, Integer.MAX_VALUE);\n        for (int j = 0; j < BLOCK_SIZE; ++j) {\n          values[i * BLOCK_SIZE + j] = value;\n        }\n      } else {\n        for (int j = 0; j < BLOCK_SIZE; ++j) {\n          values[i * BLOCK_SIZE + j] = RandomInts.randomIntBetween(random(),\n              0, (int) PackedInts.maxValue(bpv));\n        }\n      }\n    }\n\n    final Directory d = new RAMDirectory();\n    final long endPointer;\n\n    {\n      // encode\n      IndexOutput out = d.createOutput(\"test.bin\", IOContext.DEFAULT);\n      final ForUtil forUtil = new ForUtil(acceptableOverheadRatio, out);\n      \n      for (int i = 0; i < iterations; ++i) {\n        forUtil.writeBlock(\n            Arrays.copyOfRange(values, i * BLOCK_SIZE, values.length),\n            new byte[MAX_ENCODED_SIZE], out);\n      }\n      endPointer = out.getFilePointer();\n      out.close();\n    }\n\n    {\n      // decode\n      IndexInput in = d.openInput(\"test.bin\", IOContext.READONCE);\n      final ForUtil forUtil = new ForUtil(in);\n      for (int i = 0; i < iterations; ++i) {\n        if (random().nextBoolean()) {\n          forUtil.skipBlock(in);\n          continue;\n        }\n        final int[] restored = new int[MAX_DATA_SIZE];\n        forUtil.readBlock(in, new byte[MAX_ENCODED_SIZE], restored);\n        assertArrayEquals(Arrays.copyOfRange(values, i * BLOCK_SIZE, (i + 1) * BLOCK_SIZE),\n            Arrays.copyOf(restored, BLOCK_SIZE));\n      }\n      assertEquals(endPointer, in.getFilePointer());\n      in.close();\n    }\n  }\n\n","sourceOld":"  public void testEncodeDecode() throws IOException {\n    final int iterations = RandomInts.randomIntBetween(random(), 1, 1000);\n    final float acceptableOverheadRatio = random().nextFloat();\n    final int[] values = new int[(iterations - 1) * BLOCK_SIZE + ForUtil.MAX_DATA_SIZE];\n    for (int i = 0; i < iterations; ++i) {\n      final int bpv = random().nextInt(32);\n      if (bpv == 0) {\n        final int value = RandomInts.randomIntBetween(random(), 0, Integer.MAX_VALUE);\n        for (int j = 0; j < BLOCK_SIZE; ++j) {\n          values[i * BLOCK_SIZE + j] = value;\n        }\n      } else {\n        for (int j = 0; j < BLOCK_SIZE; ++j) {\n          values[i * BLOCK_SIZE + j] = RandomInts.randomIntBetween(random(),\n              0, (int) PackedInts.maxValue(bpv));\n        }\n      }\n    }\n\n    final Directory d = new RAMDirectory();\n    final long endPointer;\n\n    {\n      // encode\n      IndexOutput out = d.createOutput(\"test.bin\", IOContext.DEFAULT);\n      final ForUtil forUtil = new ForUtil(acceptableOverheadRatio, out);\n      \n      for (int i = 0; i < iterations; ++i) {\n        forUtil.writeBlock(\n            Arrays.copyOfRange(values, i * BLOCK_SIZE, values.length),\n            new byte[MAX_ENCODED_SIZE], out);\n      }\n      endPointer = out.getFilePointer();\n      out.close();\n    }\n\n    {\n      // decode\n      IndexInput in = d.openInput(\"test.bin\", IOContext.READONCE);\n      final ForUtil forUtil = new ForUtil(in);\n      for (int i = 0; i < iterations; ++i) {\n        if (random().nextBoolean()) {\n          forUtil.skipBlock(in);\n          continue;\n        }\n        final int[] restored = new int[MAX_DATA_SIZE];\n        forUtil.readBlock(in, new byte[MAX_ENCODED_SIZE], restored);\n        assertArrayEquals(Arrays.copyOfRange(values, i * BLOCK_SIZE, (i + 1) * BLOCK_SIZE),\n            Arrays.copyOf(restored, BLOCK_SIZE));\n      }\n      assertEquals(endPointer, in.getFilePointer());\n      in.close();\n    }\n  }\n\n","bugFix":null,"bugIntro":[],"isBuggy":false,"nexts":[],"revCommit":null},{"id":"71387d8cb6923eb831b17a8b734608ba2e21c653","date":1414126093,"type":4,"author":"Robert Muir","isMerge":false,"pathNew":"/dev/null","pathOld":"lucene/backward-codecs/src/test/org/apache/lucene/codecs/lucene41/TestLucene41ForUtil#testEncodeDecode().mjava","sourceNew":null,"sourceOld":"  public void testEncodeDecode() throws IOException {\n    final int iterations = RandomInts.randomIntBetween(random(), 1, 1000);\n    final float acceptableOverheadRatio = random().nextFloat();\n    final int[] values = new int[(iterations - 1) * BLOCK_SIZE + ForUtil.MAX_DATA_SIZE];\n    for (int i = 0; i < iterations; ++i) {\n      final int bpv = random().nextInt(32);\n      if (bpv == 0) {\n        final int value = RandomInts.randomIntBetween(random(), 0, Integer.MAX_VALUE);\n        for (int j = 0; j < BLOCK_SIZE; ++j) {\n          values[i * BLOCK_SIZE + j] = value;\n        }\n      } else {\n        for (int j = 0; j < BLOCK_SIZE; ++j) {\n          values[i * BLOCK_SIZE + j] = RandomInts.randomIntBetween(random(),\n              0, (int) PackedInts.maxValue(bpv));\n        }\n      }\n    }\n\n    final Directory d = new RAMDirectory();\n    final long endPointer;\n\n    {\n      // encode\n      IndexOutput out = d.createOutput(\"test.bin\", IOContext.DEFAULT);\n      final ForUtil forUtil = new ForUtil(acceptableOverheadRatio, out);\n      \n      for (int i = 0; i < iterations; ++i) {\n        forUtil.writeBlock(\n            Arrays.copyOfRange(values, i * BLOCK_SIZE, values.length),\n            new byte[MAX_ENCODED_SIZE], out);\n      }\n      endPointer = out.getFilePointer();\n      out.close();\n    }\n\n    {\n      // decode\n      IndexInput in = d.openInput(\"test.bin\", IOContext.READONCE);\n      final ForUtil forUtil = new ForUtil(in);\n      for (int i = 0; i < iterations; ++i) {\n        if (random().nextBoolean()) {\n          forUtil.skipBlock(in);\n          continue;\n        }\n        final int[] restored = new int[MAX_DATA_SIZE];\n        forUtil.readBlock(in, new byte[MAX_ENCODED_SIZE], restored);\n        assertArrayEquals(Arrays.copyOfRange(values, i * BLOCK_SIZE, (i + 1) * BLOCK_SIZE),\n            Arrays.copyOf(restored, BLOCK_SIZE));\n      }\n      assertEquals(endPointer, in.getFilePointer());\n      in.close();\n    }\n  }\n\n","bugFix":null,"bugIntro":[],"isBuggy":false,"nexts":[],"revCommit":null}],"commit2Parents":{"99eb4a732d1a908f4636ace52928876136bf1896":["a0e7ee9d0d12370e8d2b5ae0a23b6e687e018d85"],"a0e7ee9d0d12370e8d2b5ae0a23b6e687e018d85":[],"db68c63cbfaa8698b9c4475f75ed2b9c9696d238":["a0e7ee9d0d12370e8d2b5ae0a23b6e687e018d85","99eb4a732d1a908f4636ace52928876136bf1896"],"71387d8cb6923eb831b17a8b734608ba2e21c653":["db68c63cbfaa8698b9c4475f75ed2b9c9696d238"],"cd5edd1f2b162a5cfa08efd17851a07373a96817":["71387d8cb6923eb831b17a8b734608ba2e21c653"]},"commit2Childs":{"99eb4a732d1a908f4636ace52928876136bf1896":["db68c63cbfaa8698b9c4475f75ed2b9c9696d238"],"a0e7ee9d0d12370e8d2b5ae0a23b6e687e018d85":["99eb4a732d1a908f4636ace52928876136bf1896","db68c63cbfaa8698b9c4475f75ed2b9c9696d238"],"db68c63cbfaa8698b9c4475f75ed2b9c9696d238":["71387d8cb6923eb831b17a8b734608ba2e21c653"],"71387d8cb6923eb831b17a8b734608ba2e21c653":["cd5edd1f2b162a5cfa08efd17851a07373a96817"],"cd5edd1f2b162a5cfa08efd17851a07373a96817":[]},"heads":["cd5edd1f2b162a5cfa08efd17851a07373a96817"],"roots":["a0e7ee9d0d12370e8d2b5ae0a23b6e687e018d85"],"pathCommit":null}