{"path":"lucene/src/demo/org/apache/lucene/demo/IndexHTML#indexDocs(File).mjava","commits":[{"id":"9454a6510e2db155fb01faa5c049b06ece95fab9","date":1453508333,"type":1,"author":"Dawid Weiss","isMerge":false,"pathNew":"lucene/src/demo/org/apache/lucene/demo/IndexHTML#indexDocs(File).mjava","pathOld":"src/demo/org/apache/lucene/demo/IndexHTML#indexDocs(File).mjava","sourceNew":"  private static void indexDocs(File file) throws Exception {\n    if (file.isDirectory()) {\t\t\t  // if a directory\n      String[] files = file.list();\t\t  // list its files\n      Arrays.sort(files);\t\t\t  // sort the files\n      for (int i = 0; i < files.length; i++)\t  // recursively index them\n        indexDocs(new File(file, files[i]));\n\n    } else if (file.getPath().endsWith(\".html\") || // index .html files\n      file.getPath().endsWith(\".htm\") || // index .htm files\n      file.getPath().endsWith(\".txt\")) { // index .txt files\n\n      if (uidIter != null) {\n        String uid = HTMLDocument.uid(file);\t  // construct uid for doc\n\n        while (uidIter.term() != null && uidIter.term().field() == \"uid\" &&\n            uidIter.term().text().compareTo(uid) < 0) {\n          if (deleting) {\t\t\t  // delete stale docs\n            System.out.println(\"deleting \" +\n                HTMLDocument.uid2url(uidIter.term().text()));\n            reader.deleteDocuments(uidIter.term());\n          }\n          uidIter.next();\n        }\n        if (uidIter.term() != null && uidIter.term().field() == \"uid\" &&\n            uidIter.term().text().compareTo(uid) == 0) {\n          uidIter.next();\t\t\t  // keep matching docs\n        } else if (!deleting) {\t\t\t  // add new docs\n          Document doc = HTMLDocument.Document(file);\n          System.out.println(\"adding \" + doc.get(\"path\"));\n          writer.addDocument(doc);\n        }\n      } else {\t\t\t\t\t  // creating a new index\n        Document doc = HTMLDocument.Document(file);\n        System.out.println(\"adding \" + doc.get(\"path\"));\n        writer.addDocument(doc);\t\t  // add docs unconditionally\n      }\n    }\n  }\n\n","sourceOld":"  private static void indexDocs(File file) throws Exception {\n    if (file.isDirectory()) {\t\t\t  // if a directory\n      String[] files = file.list();\t\t  // list its files\n      Arrays.sort(files);\t\t\t  // sort the files\n      for (int i = 0; i < files.length; i++)\t  // recursively index them\n        indexDocs(new File(file, files[i]));\n\n    } else if (file.getPath().endsWith(\".html\") || // index .html files\n      file.getPath().endsWith(\".htm\") || // index .htm files\n      file.getPath().endsWith(\".txt\")) { // index .txt files\n\n      if (uidIter != null) {\n        String uid = HTMLDocument.uid(file);\t  // construct uid for doc\n\n        while (uidIter.term() != null && uidIter.term().field() == \"uid\" &&\n            uidIter.term().text().compareTo(uid) < 0) {\n          if (deleting) {\t\t\t  // delete stale docs\n            System.out.println(\"deleting \" +\n                HTMLDocument.uid2url(uidIter.term().text()));\n            reader.deleteDocuments(uidIter.term());\n          }\n          uidIter.next();\n        }\n        if (uidIter.term() != null && uidIter.term().field() == \"uid\" &&\n            uidIter.term().text().compareTo(uid) == 0) {\n          uidIter.next();\t\t\t  // keep matching docs\n        } else if (!deleting) {\t\t\t  // add new docs\n          Document doc = HTMLDocument.Document(file);\n          System.out.println(\"adding \" + doc.get(\"path\"));\n          writer.addDocument(doc);\n        }\n      } else {\t\t\t\t\t  // creating a new index\n        Document doc = HTMLDocument.Document(file);\n        System.out.println(\"adding \" + doc.get(\"path\"));\n        writer.addDocument(doc);\t\t  // add docs unconditionally\n      }\n    }\n  }\n\n","bugFix":null,"bugIntro":[],"isBuggy":false,"nexts":[],"revCommit":null},{"id":"790c3f61c9b891d66d919c5d10db9fa5216eb0f1","date":1274818604,"type":5,"author":"Robert Muir","isMerge":false,"pathNew":"lucene/contrib/demo/src/java/org/apache/lucene/demo/IndexHTML#indexDocs(File).mjava","pathOld":"lucene/src/demo/org/apache/lucene/demo/IndexHTML#indexDocs(File).mjava","sourceNew":"  private static void indexDocs(File file) throws Exception {\n    if (file.isDirectory()) {\t\t\t  // if a directory\n      String[] files = file.list();\t\t  // list its files\n      Arrays.sort(files);\t\t\t  // sort the files\n      for (int i = 0; i < files.length; i++)\t  // recursively index them\n        indexDocs(new File(file, files[i]));\n\n    } else if (file.getPath().endsWith(\".html\") || // index .html files\n      file.getPath().endsWith(\".htm\") || // index .htm files\n      file.getPath().endsWith(\".txt\")) { // index .txt files\n\n      if (uidIter != null) {\n        String uid = HTMLDocument.uid(file);\t  // construct uid for doc\n\n        while (uidIter.term() != null && uidIter.term().field() == \"uid\" &&\n            uidIter.term().text().compareTo(uid) < 0) {\n          if (deleting) {\t\t\t  // delete stale docs\n            System.out.println(\"deleting \" +\n                HTMLDocument.uid2url(uidIter.term().text()));\n            reader.deleteDocuments(uidIter.term());\n          }\n          uidIter.next();\n        }\n        if (uidIter.term() != null && uidIter.term().field() == \"uid\" &&\n            uidIter.term().text().compareTo(uid) == 0) {\n          uidIter.next();\t\t\t  // keep matching docs\n        } else if (!deleting) {\t\t\t  // add new docs\n          Document doc = HTMLDocument.Document(file);\n          System.out.println(\"adding \" + doc.get(\"path\"));\n          writer.addDocument(doc);\n        }\n      } else {\t\t\t\t\t  // creating a new index\n        Document doc = HTMLDocument.Document(file);\n        System.out.println(\"adding \" + doc.get(\"path\"));\n        writer.addDocument(doc);\t\t  // add docs unconditionally\n      }\n    }\n  }\n\n","sourceOld":"  private static void indexDocs(File file) throws Exception {\n    if (file.isDirectory()) {\t\t\t  // if a directory\n      String[] files = file.list();\t\t  // list its files\n      Arrays.sort(files);\t\t\t  // sort the files\n      for (int i = 0; i < files.length; i++)\t  // recursively index them\n        indexDocs(new File(file, files[i]));\n\n    } else if (file.getPath().endsWith(\".html\") || // index .html files\n      file.getPath().endsWith(\".htm\") || // index .htm files\n      file.getPath().endsWith(\".txt\")) { // index .txt files\n\n      if (uidIter != null) {\n        String uid = HTMLDocument.uid(file);\t  // construct uid for doc\n\n        while (uidIter.term() != null && uidIter.term().field() == \"uid\" &&\n            uidIter.term().text().compareTo(uid) < 0) {\n          if (deleting) {\t\t\t  // delete stale docs\n            System.out.println(\"deleting \" +\n                HTMLDocument.uid2url(uidIter.term().text()));\n            reader.deleteDocuments(uidIter.term());\n          }\n          uidIter.next();\n        }\n        if (uidIter.term() != null && uidIter.term().field() == \"uid\" &&\n            uidIter.term().text().compareTo(uid) == 0) {\n          uidIter.next();\t\t\t  // keep matching docs\n        } else if (!deleting) {\t\t\t  // add new docs\n          Document doc = HTMLDocument.Document(file);\n          System.out.println(\"adding \" + doc.get(\"path\"));\n          writer.addDocument(doc);\n        }\n      } else {\t\t\t\t\t  // creating a new index\n        Document doc = HTMLDocument.Document(file);\n        System.out.println(\"adding \" + doc.get(\"path\"));\n        writer.addDocument(doc);\t\t  // add docs unconditionally\n      }\n    }\n  }\n\n","bugFix":null,"bugIntro":[],"isBuggy":false,"nexts":[],"revCommit":null}],"commit2Parents":{"a0e7ee9d0d12370e8d2b5ae0a23b6e687e018d85":[],"cd5edd1f2b162a5cfa08efd17851a07373a96817":["790c3f61c9b891d66d919c5d10db9fa5216eb0f1"],"790c3f61c9b891d66d919c5d10db9fa5216eb0f1":["9454a6510e2db155fb01faa5c049b06ece95fab9"],"9454a6510e2db155fb01faa5c049b06ece95fab9":["a0e7ee9d0d12370e8d2b5ae0a23b6e687e018d85"]},"commit2Childs":{"a0e7ee9d0d12370e8d2b5ae0a23b6e687e018d85":["9454a6510e2db155fb01faa5c049b06ece95fab9"],"cd5edd1f2b162a5cfa08efd17851a07373a96817":[],"790c3f61c9b891d66d919c5d10db9fa5216eb0f1":["cd5edd1f2b162a5cfa08efd17851a07373a96817"],"9454a6510e2db155fb01faa5c049b06ece95fab9":["790c3f61c9b891d66d919c5d10db9fa5216eb0f1"]},"heads":["cd5edd1f2b162a5cfa08efd17851a07373a96817"],"roots":["a0e7ee9d0d12370e8d2b5ae0a23b6e687e018d85"],"pathCommit":null}